CHANGES.txt
LICENSE.txt
MANIFEST.in
README.rst
setup.cfg
setup.py
django_static_root_finder/__init__.py
django_static_root_finder/finders.py
django_static_root_finder.egg-info/PKG-INFO
django_static_root_finder.egg-info/SOURCES.txt
django_static_root_finder.egg-info/dependency_links.txt
django_static_root_finder.egg-info/pbr.json
django_static_root_finder.egg-info/requires.txt
django_static_root_finder.egg-info/top_level.txt