Metadata-Version: 1.0
Name: django-static-root-finder
Version: 0.2.0
Summary: A static files finder to find files in the STATIC_ROOT directory.
Home-page: https://github.com/ubuntudesign/django-static-root-finder
Author: Robin
Author-email: robin.winslow@canonical.com
License: UNKNOWN
Platform: UNKNOWN
